{
  "layout": [
    ["W", "W", "W", "W", "W", "W", "W", "W", "W", "W", "W", "W", "W", "W", "W", "W", "W", "W", "W", "W", "W", "W", "W", "W", "W", "W", "W", "W", "W", "W"],
    ["W", "O", "F", "F", "F", "F", "W", "F", "F", "F", "F", "F", "F", "W", "F", "F", "F", "W", "E", "E", "W", "F", "W", "F", "F", "F", "F", "F", "F", "W"],
    ["W", "F", "W", "W", "W", "F", "W", "F", "F", "W", "F", "F", "F", "W", "W", "W", "W", "W", "E", "E", "W", "F", "F", "F", "F", "F", "W", "F", "F", "W"],
    ["W", "F", "F", "W", "F", "F", "W", "W", "W", "W", "W", "F", "W", "W", "F", "F", "F", "W", "E", "E", "F", "F", "W", "W", "W", "F", "W", "W", "W", "W"],
    ["W", "F", "F", "W", "F", "F", "W", "F", "F", "F", "F", "F", "F", "W", "F", "F", "F", "W", "E", "E", "W", "F", "F", "W", "F", "F", "F", "W", "W", "W"],
    ["W", "F", "W", "W", "W", "F", "W", "F", "W", "W", "F", "W", "F", "W", "W", "F", "W", "W", "W", "W", "W", "F", "F", "W", "F", "O", "F", "W", "W", "W"],
    ["W", "F", "F", "F", "F", "F", "F", "F", "W", "W", "F", "F", "F", "F", "F", "F", "F", "F", "F", "F", "F", "F", "F", "W", "F", "F", "F", "W", "W", "W"],
    ["W", "W", "W", "W", "W", "W", "W", "W", "W", "W", "W", "W", "W", "W", "W", "W", "W", "W", "W", "W", "W", "W", "W", "W", "W", "W", "W", "W", "W", "W"]
  ],
  "player": {
    "spawn": { "x": 15, "y": 3 },
    "camera": {
      "yaw": 180
    }
  },
  "objectives": [
    { "id":"reach.firstSpecialTile", "mandatory":true,
      "when": { "type":"reach", "x":1, "y":1 },
      "ui": "Reach the tile (1,1)"
    },
    { "id":"reach.secondSpecialTile", "mandatory":true,
      "when": { "type":"reach", "x":25, "y":5 },
      "ui": "Reach the tile (25,5)"
    }
  ]
}